Workbook

Sheet Instrucciones
A1: RQM Complemento módulo de Consulta de Logs + Marca de Oferta – T29 Casos de prueba
A2: Rama: RQM-ComplementoLogs+SaleOff · BD de pruebas: GML0999\SQLEXPRESS01 · Sitio: https://localhost:6001 · Usuario: admin
A4: Cómo usar:
A5: 1. Ejecutar los scripts de Despliegue en orden (01–19) en la BD de pruebas antes de iniciar.
A6: 2. Hoja 'Casos de prueba': llenar solo las columnas en amarillo: Resultado (lista: OK / Corrección / Pendiente / No aplica), Observaciones, Probado por y Fecha.
A7: 3. Hoja 'Regresión acumulada': repetir al final de la ejecución completa.
A8: 4. Hoja 'Datos de prueba': datos creados durante el RQM que se restauran o documentan en T30.
A9: 5. Hoja 'Resumen': se calcula sola.
A11: Casos E1/E2 armados desde el plan de trabajo y los commits de la rama; contrastar con el detalle del Proyecto 'Desarrollos Promos Aldebaran' y completar si falta algo.
A12: Fila de ejemplo de llenado: ID E3-01 → Resultado: OK · Observaciones: 'Conteo 12 = BD' · Probado por: Claude Chat · Fecha: 2026-10-25

Sheet Casos de prueba
A1: ID | B1: Entrega | C1: Tarea | D1: Pantalla / objeto | E1: Rol | F1: Precondición | G1: Pasos | H1: Resultado esperado | I1: Verificación en BD | J1: Resultado | K1: Observaciones | L1: Probado por | M1: Fecha
A2: E1-01 | B2: E1 | C2: T1 | D2: BD - log.Logs / log.track | E2: DBA | F2: Script 01 ejecutado | G2: Ejecutar 01 - Indices Log y Track.sql dos veces. | H2: Sin errores; segunda ejecución no recrea nada. | I2: SELECT name FROM sys.indexes WHERE name IN ('IX_Logs_TimeStamp','IX_Logs_Template_TimeStamp','IX_track_Entity_Date','IX_track_Entity_Key'); -- 4 filas
A3: E1-02 | B3: E1 | C3: T1 | D3: Aplicación (escritura de logs) | E3: admin | F3: Índices creados | G3: Navegar la app y generar un error controlado; guardar un pedido. | H3: Serilog y Track siguen escribiendo sin errores. | I3: SELECT TOP 5 * FROM log.Logs ORDER BY TimeStamp DESC; SELECT TOP 5 * FROM log.track ORDER BY 1 DESC;
A4: E1-03 | B4: E1 | C4: T2a | D4: Conexiones FTP / Autómata / SMTP | E4: admin | F4: — | G4: Editar la contraseña de FTP SERVIDOR-PRUEBA-T2, de la conexión del autómata y la clave SMTP; abrir el Track de cada una. | H4: Track muestra '********' y '******** (modificada)'; nunca el valor ni un hash. | I4: SELECT TOP 10 * FROM log.track WHERE ENTITY_NAME LIKE '%Connection%' OR ENTITY_NAME LIKE '%NotificationProvider%' ORDER BY 1 DESC;
A5: E1-04 | B5: E1 | C5: T2a | D5: BD - histórico log.track | E5: DBA | F5: Script 02 ejecutado | G5: Ejecutar 02 - Ofuscar historico Track.sql (re-ejecutable). | H5: No quedan contraseñas en claro en el histórico. | I5: Buscar en log.track textos de clave conocidos (ej. clave SMTP anterior): 0 filas.
A6: E1-05 | B6: E1 | C6: T2b | D6: Track - 19 entidades ITrackeable | E6: admin | F6: — | G6: Ejecutar una acción por entidad (cierre/modificación de pedido, modificación de reserva, despacho, traslado, OC, ajuste OC, tolerancias, alarma de tránsito, usuarios-alarma, notificaciones, patrones y destinatarios del autómata, conexiones). | H6: Cada acción genera su movimiento en Track con usuario y fecha. | I6: Scripts\Pruebas 04 - Pruebas T2 Track.sql
A7: E1-06 | B7: E1 | C7: T3 | D7: BD - consulta de visualización de alarmas | E7: DBA | F7: Script 03 | G7: Ejecutar SP_GET_ALARM_LOG_TYPES y SP_GET_ALARM_LOG con rango de fechas. | H7: 10 tipos; rango obligatorio; paginación con total. | I7: Pruebas P03 (21 casos)
A8: E1-07 | B8: E1 | C8: T3b | D8: Alarmas de inventario - ciclo de vida | E8: admin | F8: Script 04; referencia con mínimo | G8: Bajar el disponible bajo el mínimo; volver a moverlo sin cambiar la cantidad; confirmar OC que repone. | H8: Nace una alarma; si la condición se repite se refresca y borra visualizaciones; muere al confirmar OC. Cada evento queda en INVENTORY_ALARM_LOG con estado anterior/nuevo y origen. | I8: SELECT TOP 20 * FROM dbo.INVENTORY_ALARM_LOG ORDER BY 1 DESC;
A9: E1-08 | B9: E1 | C9: T3b | D9: Alarma bodega local | E9: admin | F9: Referencia con mínimo en Bodega Local | G9: Mover inventario de Bodega Local bajo el mínimo. | H9: Solo evalúa Bodega Local; refresca y registra log igual que las demás. | I9: INVENTORY_ALARM_LOG con ALARM_TYPE_CODE = 'MINIMUM_LOCAL_WAREHOUSE'
A10: E1-09 | B10: E1 | C10: T3c | D10: Job 'Verificacion Alarmas' | E10: DBA | F10: Script 05 (permisos msdb) | G10: Ejecutar el job manualmente. | H10: Refrescos solo si cambió la cantidad; inactivaciones directas con origen 'Proceso programado - depuración'. | I10: Pruebas P04 (J1–J3)
A11: E1-10 | B11: E1 | C11: T4/T5 | D11: Consulta de Log > Visualización de alarmas (Órdenes, Pedidos, Reservas) | E11: Rol de cada contexto | F11: Script 06 | G11: Abrir cada contexto; filtrar por fechas y texto; abrir el diálogo de visualizaciones. Abrir un contexto sin rol. | H11: Totales = SP; diálogo con quién y cuándo visualizó. Sin rol: /unauthorized. | I11: Pruebas P05
A12: E1-11 | B12: E1 | C12: T4/T5 | D12: Log de inventarios > Inactivaciones y refrescos | E12: Log de inventarios | F12: — | G12: Filtrar por tipo de alarma, evento, fechas y texto. | H12: Muestra estado anterior → nuevo y origen; totales = BD. | I12: SELECT COUNT(*) FROM dbo.INVENTORY_ALARM_LOG WHERE EVENT_DATE BETWEEN ...
A13: E1-12 | B13: E1 | C13: T6/T7 | D13: Log del sistema > Track | E13: Log del sistema | F13: Scripts 07, 08 | G13: Buscar por objeto (pedido 39471) sin entidad; buscar por entidad sin objeto; aplicar fechas, acción y usuario; abrir detalle. | H13: Movimientos de todas las entidades del pedido; detalle campo/anterior/nuevo con cambios resaltados y descripción de Id. | I13: Pruebas P06
... A63: E4-12 | B63: E4 | C63: C4 | D63: Pruebas unitarias | E63: Desarrollo | F63: — | G63: dotnet test sobre Aldebaran.Application.Services.Tests. | H63: Todas en verde. | I63: —

Sheet Regresión acumulada
A1: ID | B1: Área | C1: Pasos | D1: Resultado esperado | E1: Resultado | F1: Observaciones | G1: Probado por | H1: Fecha
A2: R-01 | B2: Logs existentes de OC, pedidos y reservas | C2: Abrir cada log con rango amplio | D2: Cargan sin errores; totales = BD
A3: R-02 | B3: Tablero de notificaciones y alarmas | C3: Abrir todas las pestañas y marcar visualizado | D3: Cargan; marcar visualizado funciona y queda en el log
A4: R-03 | B4: Reporte de cantidades mínimas y correo con Excel | C4: Generar el reporte y el correo | D4: Datos = BD; Excel con marca $ BOMBA
A5: R-04 | B5: Pedido: crear / modificar / cancelar / cerrar | C5: Flujo completo | D5: Sin errores; queda en Track y logs
A6: R-05 | B6: OC: crear / modificar / cancelar / confirmar | C6: Flujo completo | D6: Sin errores; alarmas y log de ajustes correctos
A7: R-06 | B7: Reserva: crear / modificar / cancelar / pasar a pedido | C7: Flujo completo | D7: Sin errores; Track y logs
A8: R-07 | B8: Permisos | C8: Usuario con un solo rol por pantalla nueva | D8: Ve solo lo que su rol permite; tildes de roles correctas

Sheet Datos de prueba
A1: Dato | B1: Detalle | C1: Acción al cierre (T30)
A2: Precio bomba | B2: HO-13 (ITEM_ID 2554, ancho embalaje 29, original 28) y ASTON-STY (2047) | C2: Restaurar al cierre
A3: Remitente SMTP pruebas | B3: 'Catalogos Promocionales T2' | C3: Devolver a 'Catalogos Promocionales' (clave la carga Andrés)
A4: Conexión autómata / FTP / patrón | B4: SERVIDOR-PRUEBA-T2, ftp.prueba-t2.invalid, PATRON PRUEBA T2 NO USAR (inactivos) | C4: Eliminar o dejar inactivos
A5: Pedidos y reservas | B5: Reserva 92; pedidos 39469, 39463 (cancelado), 39175 (cerrado), 39471 (cancelado, VA-196 Azul) y los de T24 | C5: Documentar en el cierre
A6: Alarmas / OC / tolerancias | B6: Alarmas 825 y 826; OC 752 confirmada; ajuste OC 742 devuelto; tolerancia 351–400 en 0,06 | C6: Restaurar tolerancia si aplica
A7: Cliente para correos | B7: Cédula 79872389 (de Andrés) | C7: —

Sheet Resumen
A1: Entrega | B1: Casos | C1: OK | D1: Corrección | E1: Pendiente | F1: No aplica | G1: Sin ejecutar | H1: % OK
A2: E1 | B2: =COUNTIF('Casos de prueba'!$B$2:$B$63,A2) -> 16 | C2: =COUNTIFS('Casos de prueba'!$B$2:$B$63,$A2,'Casos de prueba'!$J$2:$J$63,"OK") -> 0 | D2: =COUNTIFS('Casos de prueba'!$B$2:$B$63,$A2,'Casos de prueba'!$J$2:$J$63,"Corrección") -> 0 | E2: =COUNTIFS('Casos de prueba'!$B$2:$B$63,$A2,'Casos de prueba'!$J$2:$J$63,"Pendiente") -> 0 | F2: =COUNTIFS('Casos de prueba'!$B$2:$B$63,$A2,'Casos de prueba'!$J$2:$J$63,"No aplica") -> 0 | G2: =B2-SUM(C2:F2) -> 16 | H2: =IF(B2=0,0,C2/B2) -> 0
A3: E2 | B3: =COUNTIF('Casos de prueba'!$B$2:$B$63,A3) -> 6 | C3: =COUNTIFS('Casos de prueba'!$B$2:$B$63,$A3,'Casos de prueba'!$J$2:$J$63,"OK") -> 0 | D3: =COUNTIFS('Casos de prueba'!$B$2:$B$63,$A3,'Casos de prueba'!$J$2:$J$63,"Corrección") -> 0 | E3: =COUNTIFS('Casos de prueba'!$B$2:$B$63,$A3,'Casos de prueba'!$J$2:$J$63,"Pendiente") -> 0 | F3: =COUNTIFS('Casos de prueba'!$B$2:$B$63,$A3,'Casos de prueba'!$J$2:$J$63,"No aplica") -> 0 | G3: =B3-SUM(C3:F3) -> 6 | H3: =IF(B3=0,0,C3/B3) -> 0
A4: E3 | B4: =COUNTIF('Casos de prueba'!$B$2:$B$63,A4) -> 28 | C4: =COUNTIFS('Casos de prueba'!$B$2:$B$63,$A4,'Casos de prueba'!$J$2:$J$63,"OK") -> 0 | D4: =COUNTIFS('Casos de prueba'!$B$2:$B$63,$A4,'Casos de prueba'!$J$2:$J$63,"Corrección") -> 0 | E4: =COUNTIFS('Casos de prueba'!$B$2:$B$63,$A4,'Casos de prueba'!$J$2:$J$63,"Pendiente") -> 0 | F4: =COUNTIFS('Casos de prueba'!$B$2:$B$63,$A4,'Casos de prueba'!$J$2:$J$63,"No aplica") -> 0 | G4: =B4-SUM(C4:F4) -> 28 | H4: =IF(B4=0,0,C4/B4) -> 0
A5: E4 | B5: =COUNTIF('Casos de prueba'!$B$2:$B$63,A5) -> 12 | C5: =COUNTIFS('Casos de prueba'!$B$2:$B$63,$A5,'Casos de prueba'!$J$2:$J$63,"OK") -> 0 | D5: =COUNTIFS('Casos de prueba'!$B$2:$B$63,$A5,'Casos de prueba'!$J$2:$J$63,"Corrección") -> 0 | E5: =COUNTIFS('Casos de prueba'!$B$2:$B$63,$A5,'Casos de prueba'!$J$2:$J$63,"Pendiente") -> 0 | F5: =COUNTIFS('Casos de prueba'!$B$2:$B$63,$A5,'Casos de prueba'!$J$2:$J$63,"No aplica") -> 0 | G5: =B5-SUM(C5:F5) -> 12 | H5: =IF(B5=0,0,C5/B5) -> 0
A6: Total | B6: =SUM(B2:B5) -> 62 | C6: =SUM(C2:C5) -> 0 | D6: =SUM(D2:D5) -> 0 | E6: =SUM(E2:E5) -> 0 | F6: =SUM(F2:F5) -> 0 | G6: =SUM(G2:G5) -> 62 | H6: =IF(B6=0,0,C6/B6) -> 0
A8: Regresión: casos | B8: =COUNTA('Regresión acumulada'!$A$2:$A$8) -> 7
A9: Regresión: OK | B9: =COUNTIF('Regresión acumulada'!$E$2:$E$8,"OK") -> 0
